common_web-1.0.1.dist-info/licenses/LICENSE
constants/__init__.py
constants/festival.py
dto/__init__.py
dto/res_dto.py
exception/__init__.py
exception/auth_exception.py
exception/business_exception.py
handler/__init__.py
handler/exception_handler.py
utils/__init__.py
utils/date_util.py
utils/festival_util.py
utils/file_util.py
utils/http_util.py
utils/json_util.py
common_web-1.0.1.dist-info/METADATA
common_web-1.0.1.dist-info/WHEEL
common_web-1.0.1.dist-info/top_level.txt
common_web-1.0.1.dist-info/RECORD
