Metadata-Version: 2.4
Name: common-web
Version: 1.0.1
Summary: this is common for base
Author-email: Cloud Bian <cloudbian@139.com>
License: MIT
Classifier: License :: OSI Approved :: MIT License
Requires-Python: >=3.10
License-File: LICENSE
Dynamic: license-file
